setup.py
reinforce/__init__.py
reinforce/learn.py
reinforce/mdpmodel.py
reinforce/mdpsolve.py
reinforce/parse.py
reinforce.egg-info/PKG-INFO
reinforce.egg-info/SOURCES.txt
reinforce.egg-info/dependency_links.txt
reinforce.egg-info/top_level.txt