Metadata-Version: 1.0
Name: reinforce
Version: 0.1.0
Summary: plug and play reinforcement learning
Home-page: http://github.com/nathanepstein/reinforce
Author: Nathan Epstein
Author-email: ne2210@columbia.edu
License: MIT
Platform: UNKNOWN
